django_large_image/__init__.py
django_large_image/apps.py
django_large_image/cache.py
django_large_image/tilesource.py
django_large_image/urls.py
django_large_image/utilities.py
django_large_image/rest/__init__.py
django_large_image/rest/base.py
django_large_image/rest/data.py
django_large_image/rest/metadata.py
django_large_image/rest/params.py
django_large_image/rest/renderers.py
django_large_image/rest/serializers.py
django_large_image/rest/standalone.py
django_large_image/rest/tiles.py
django_large_image/rest/viewsets.py
django_large_image/static/django_large_image/js/cesium.js
django_large_image/static/django_large_image/js/geojs/1.8.3/geo.min.js
django_large_image/static/django_large_image/styles/cesium.css
django_large_image/static/django_large_image/styles/style.css
django_large_image/templates/admin/django_large_image/_include/geojs.html
django_large_image/templates/django_large_image/base.html
django_large_image/templates/django_large_image/cesiumViewer.html
django_large_image/templates/django_large_image/geojsViewer.html
django_large_image/templates/django_large_image/_include/base.html
django_large_image/templates/django_large_image/_include/cesium.html
django_large_image/templates/django_large_image/_include/colors.html
django_large_image/templates/django_large_image/_include/geojs.html
django_large_image-0.10.2.dist-info/METADATA
django_large_image-0.10.2.dist-info/WHEEL
django_large_image-0.10.2.dist-info/entry_points.txt
django_large_image-0.10.2.dist-info/licenses/LICENSE
django_large_image-0.10.2.dist-info/licenses/NOTICE
django_large_image-0.10.2.dist-info/RECORD
