Metadata-Version: 2.4
Name: django-large-image
Version: 0.10.2
Summary: Dynamic tile server in Django built on top of large-image (and GDAL)
Project-URL: Repository, https://github.com/girder/django-large-image
Project-URL: Bug Reports, https://github.com/girder/django-large-image/issues
Maintainer-email: "Kitware, Inc." <kitware@kitware.com>
License-Expression: Apache-2.0
License-File: LICENSE
License-File: NOTICE
Classifier: Development Status :: 3 - Alpha
Classifier: Environment :: Web Environment
Classifier: Framework :: Django
Classifier: Framework :: Django :: 3.0
Classifier: Intended Audience :: Developers
Classifier: Operating System :: OS Independent
Classifier: Programming Language :: Python
Classifier: Programming Language :: Python :: 3
Classifier: Programming Language :: Python :: 3.8
Requires-Python: >=3.8
Requires-Dist: django
Requires-Dist: djangorestframework
Requires-Dist: drf-spectacular
Requires-Dist: filelock
Requires-Dist: large-image>=1.16.2
Provides-Extra: colormaps
Requires-Dist: cmocean; extra == 'colormaps'
Requires-Dist: matplotlib; extra == 'colormaps'
